pumpy.py
setup.py
pumpy.egg-info/PKG-INFO
pumpy.egg-info/SOURCES.txt
pumpy.egg-info/dependency_links.txt
pumpy.egg-info/requires.txt
pumpy.egg-info/top_level.txt