Metadata-Version: 1.1
Name: pumpy
Version: 1.1.3
Summary: Python RS-232 interface for Harvard syringe pumps
Home-page: https://github.com/tomwphillips/pumpy
Author: Tom W Phillips
Author-email: me@tomwphillips.co.uk
License: MIT
Platform: UNKNOWN
Classifier: Programming Language :: Python
Classifier: Operating System :: OS Independent
Classifier: Intended Audience :: Science/Research
Classifier: License :: OSI Approved :: MIT License
Classifier: Topic :: Scientific/Engineering
